dotplot/__init__.py
dotplot/annotation_bands.py
dotplot/cmap.py
dotplot/core.py
dotplot/exceptions.py
dotplot/hierarchical.py
dotplot/utils.py
python_dotplot-0.0.1.dist-info/LICENSE
python_dotplot-0.0.1.dist-info/METADATA
python_dotplot-0.0.1.dist-info/WHEEL
python_dotplot-0.0.1.dist-info/top_level.txt
python_dotplot-0.0.1.dist-info/RECORD
